{"version": "https://jsonfeed.org/version/1", "title": "Thomas Wilde Tech", "home_page_url": "https://thomaswildetech.com/", "feed_url": "https://thomaswildetech.com/feed_json_created.json", "description": "A place to share my tech knowledge and projects", "icon": null, "authors": [], "language": "en", "items": [{"id": "https://thomaswildetech.com/blog/2025/02/18/creating-a-grafana-dashboard-for-npm-with-geoip-data/", "url": "https://thomaswildetech.com/blog/2025/02/18/creating-a-grafana-dashboard-for-npm-with-geoip-data/", "title": "Creating a Grafana Dashboard for NPM with GeoIP Data", "content_html": "Setting up Nginx Proxy Manager with Grafana\n", "image": null, "date_published": "2025-02-18T00:00:00+00:00", "authors": [{"name": "Thomas Wilde"}], "tags": ["Grafana", "Linux", "Logs", "Nginx Proxy Manager", "Self Hosted"]}, {"id": "https://thomaswildetech.com/blog/2025/02/16/an-easy-and-efficient-way-to-patch-and-entity-with-an-incoming-map/", "url": "https://thomaswildetech.com/blog/2025/02/16/an-easy-and-efficient-way-to-patch-and-entity-with-an-incoming-map/", "title": "An easy and efficient way to Patch and entity with an incoming Map", "content_html": "Spring Boot Patch\n", "image": null, "date_published": "2025-02-16T00:00:00+00:00", "authors": [{"name": "Thomas Wilde"}], "tags": ["Patch", "Spring Boot", "Spring Boot"]}, {"id": "https://thomaswildetech.com/blog/2025/02/12/cockpit/", "url": "https://thomaswildetech.com/blog/2025/02/12/cockpit/", "title": "Cockpit", "content_html": "Setting up Cockpit\n", "image": null, "date_published": "2025-02-12T00:00:00+00:00", "authors": [{"name": "Thomas Wilde"}], "tags": ["Cockpit", "Immich", "Linux", "RAID", "Self Hosted"]}, {"id": "https://thomaswildetech.com/blog/2025/02/12/mounting-nfts-external-drive/", "url": "https://thomaswildetech.com/blog/2025/02/12/mounting-nfts-external-drive/", "title": "Mounting NFTS external drive", "content_html": "Mounting an external drive to your server\n", "image": null, "date_published": "2025-02-12T00:00:00+00:00", "authors": [{"name": "Thomas Wilde"}], "tags": ["External Drive", "Linux", "NTSF", "Self Hosted"]}, {"id": "https://thomaswildetech.com/blog/2025/02/12/install-ubuntu/", "url": "https://thomaswildetech.com/blog/2025/02/12/install-ubuntu/", "title": "Install Ubuntu", "content_html": "Mounting an external drive to your server\n", "image": null, "date_published": "2025-02-12T00:00:00+00:00", "authors": [{"name": "Thomas Wilde"}], "tags": ["External Drive", "Linux", "NTSF", "Self Hosted"]}, {"id": "https://thomaswildetech.com/blog/2025/02/01/using-kopia-to-setup-snapshot-backups/", "url": "https://thomaswildetech.com/blog/2025/02/01/using-kopia-to-setup-snapshot-backups/", "title": "Using Kopia to setup snapshot backups", "content_html": "Setting up Kopia for snapshot backups of data\n", "image": null, "date_published": "2025-02-01T00:00:00+00:00", "authors": [{"name": "Thomas Wilde"}], "tags": ["Immich", "Kopia", "Linux", "Self Hosted"]}, {"id": "https://thomaswildetech.com/blog/2025/01/31/using-goaccess-with-nginx-proxy-manager-npm-to-visuallize-logs/", "url": "https://thomaswildetech.com/blog/2025/01/31/using-goaccess-with-nginx-proxy-manager-npm-to-visuallize-logs/", "title": "Using GoAccess with Nginx Proxy Manager (NPM) to visuallize logs.", "content_html": "Visualizng nginx proxy manager logs with GoAccess\n", "image": null, "date_published": "2025-01-31T00:00:00+00:00", "authors": [{"name": "Thomas Wilde"}], "tags": ["GoAccess", "Linux", "Logs", "Nginx Proxy Manager", "Self Hosted"]}, {"id": "https://thomaswildetech.com/blog/2025/01/30/hosting-local-https-with-trusted-cert-from-cloudflare-with-npm/", "url": "https://thomaswildetech.com/blog/2025/01/30/hosting-local-https-with-trusted-cert-from-cloudflare-with-npm/", "title": "Hosting local https with trusted cert from Cloudflare with NPM", "content_html": "How to run Immich or any other service locally on https with a TRUSTED certificate using Nginx Proxy Manager.\n", "image": null, "date_published": "2025-01-30T00:00:00+00:00", "authors": [{"name": "Thomas Wilde"}], "tags": ["Immich", "Linux", "Linux", "Nginx Proxy Manager", "Self Hosted", "https", "local https"]}, {"id": "https://thomaswildetech.com/blog/2025/01/30/hosting-local-https-with-trusted-cert-from-cloudflare-with-caddy/", "url": "https://thomaswildetech.com/blog/2025/01/30/hosting-local-https-with-trusted-cert-from-cloudflare-with-caddy/", "title": "Hosting local https with trusted cert from Cloudflare with Caddy", "content_html": "How to run Immich or any other service locally on https with a TRUSTED certificate using Caddy.\n", "image": null, "date_published": "2025-01-30T00:00:00+00:00", "authors": [{"name": "Thomas Wilde"}], "tags": ["Caddy", "Immich", "Linux", "Linux", "Self Hosted", "https", "local https"]}, {"id": "https://thomaswildetech.com/blog/2025/01/14/listening-to-events-in-springboot/", "url": "https://thomaswildetech.com/blog/2025/01/14/listening-to-events-in-springboot/", "title": "Listening to events in SpringBoot", "content_html": "Spring Boot Listerns\n", "image": null, "date_published": "2025-01-14T00:00:00+00:00", "authors": [{"name": "Thomas Wilde"}], "tags": ["@EntityListeners", "@RepositoryEventHandler", "Aspects", "Auditing", "Spring Boot", "Spring Boot"]}, {"id": "https://thomaswildetech.com/blog/2025/01/10/hosting-local-https-app/", "url": "https://thomaswildetech.com/blog/2025/01/10/hosting-local-https-app/", "title": "Hosting local https app", "content_html": "How to run Immich or any other service locally on https\n", "image": null, "date_published": "2025-01-10T00:00:00+00:00", "authors": [{"name": "Thomas Wilde"}], "tags": ["Caddy", "Immich", "Linux", "Linux", "Self Hosted", "https", "local https"]}, {"id": "https://thomaswildetech.com/blog/2025/01/06/ms-sql-installation/", "url": "https://thomaswildetech.com/blog/2025/01/06/ms-sql-installation/", "title": "MS SQL Installation", "content_html": "Notes on MS Sql Installation\n", "image": null, "date_published": "2025-01-06T00:00:00+00:00", "authors": [{"name": "Thomas Wilde"}], "tags": ["MSSQL", "SQL", "SQL"]}, {"id": "https://thomaswildetech.com/blog/2025/01/06/sudo-two-factor-authentication/", "url": "https://thomaswildetech.com/blog/2025/01/06/sudo-two-factor-authentication/", "title": "Sudo Two-Factor Authentication", "content_html": "How to set up 2FA for sudo access\n", "image": null, "date_published": "2025-01-06T00:00:00+00:00", "authors": [{"name": "Thomas Wilde"}], "tags": ["2FA", "Linux", "Linux", "MFA"]}, {"id": "https://thomaswildetech.com/blog/2025/01/02/stripe-fireship-demo/", "url": "https://thomaswildetech.com/blog/2025/01/02/stripe-fireship-demo/", "title": "Stripe Fireship Demo", "content_html": "Creating a demo Stripe project\n", "image": null, "date_published": "2025-01-02T00:00:00+00:00", "authors": [{"name": "Thomas Wilde"}], "tags": ["Hono.js", "Stripe", "Stripe", "Supabase"]}, {"id": "https://thomaswildetech.com/blog/2024/12/19/how-to-use-a-firebase-as-a-auth-provider-untested/", "url": "https://thomaswildetech.com/blog/2024/12/19/how-to-use-a-firebase-as-a-auth-provider-untested/", "title": "How to use a FireBase as a Auth provider (untested)", "content_html": "Quick thoughts on using Firebase to Authenticate with SpringBoot\n", "image": null, "date_published": "2024-12-19T00:00:00+00:00", "authors": [{"name": "Thomas Wilde"}], "tags": ["Authentication", "Firebase", "Spring Boot", "Spring Boot"]}, {"id": "https://thomaswildetech.com/blog/2024/12/18/fireshipio-tutorial/", "url": "https://thomaswildetech.com/blog/2024/12/18/fireshipio-tutorial/", "title": "Fireship.io tutorial", "content_html": "Flutter Firebase Crud tutorial\n", "image": null, "date_published": "2024-12-18T00:00:00+00:00", "authors": [{"name": "Thomas Wilde"}], "tags": ["Flutter", "Flutter"]}, {"id": "https://thomaswildetech.com/blog/2024/12/17/using-ubuntu-snap-store/", "url": "https://thomaswildetech.com/blog/2024/12/17/using-ubuntu-snap-store/", "title": "Using Ubuntu Snap Store", "content_html": "What is Immich and how do I deploy it?\n", "image": null, "date_published": "2024-12-17T00:00:00+00:00", "authors": [{"name": "Thomas Wilde"}], "tags": ["CasaOS", "CasaOS", "Immich", "Self Hosted", "Umbrel"]}, {"id": "https://thomaswildetech.com/blog/2024/12/17/using-umbrel/", "url": "https://thomaswildetech.com/blog/2024/12/17/using-umbrel/", "title": "Using Umbrel", "content_html": "What is Immich and how do I deploy it?\n", "image": null, "date_published": "2024-12-17T00:00:00+00:00", "authors": [{"name": "Thomas Wilde"}], "tags": ["CasaOS", "CasaOS", "Immich", "Self Hosted"]}, {"id": "https://thomaswildetech.com/blog/2024/12/17/using-umbrel/", "url": "https://thomaswildetech.com/blog/2024/12/17/using-umbrel/", "title": "Using Umbrel", "content_html": "What is Immich and how do I deploy it?\n", "image": null, "date_published": "2024-12-17T00:00:00+00:00", "authors": [{"name": "Thomas Wilde"}], "tags": ["Immich", "Immich", "Self Hosted", "Umbrel", "Umbrel"]}, {"id": "https://thomaswildetech.com/blog/2024/12/17/what-is-immich/", "url": "https://thomaswildetech.com/blog/2024/12/17/what-is-immich/", "title": "What is Immich?", "content_html": "What is Immich and how do I deploy it?\n", "image": null, "date_published": "2024-12-17T00:00:00+00:00", "authors": [{"name": "Thomas Wilde"}], "tags": ["CasaOS", "CloudFlare", "Cloudron", "Docker", "Immich", "Immich", "Portainer", "Self Hosted", "Umbrel", "YouTube", "YouTube"]}]}